{
  "kenkyuusei7_1": [
    {
      "identity": "aikawa_honoka",
      "name": "相川暖花",
      "generation": 7,
      "keywords": [
        "あいかわほのか",
        "ほのののブログ",
        "ほのののぶろぐ",
        "ほののののふろぐ"
      ]
    },
    {
      "identity": "asai_yuka",
      "name": "浅井裕華",
      "generation": 7,
      "keywords": [
        "浅井裕華でーす",
        "浅井裕華です",
        "ゆうかたんこと浅井裕華でした"
      ]
    },
    {
      "identity": "ota_ayaka",
      "name": "太田彩夏",
      "generation": 7,
      "keywords": ["太田彩夏です", "あやめろディ"]
    },
    {
      "identity": "obata_yuna",
      "name": "小畑優奈",
      "generation": 7,
      "keywords": ["小畑優奈です"]
    },
    {
      "identity": "kataoka_narumi",
      "name": "片岡成美",
      "generation": 7,
      "keywords": ["片岡なるちゃんの毎日", "なるちゃんの毎日"]
    }
  ],
  "kenkyuusei7_2": [
    {
      "identity": "kawasaki_narumi",
      "name": "川崎成美",
      "generation": 7,
      "keywords": ["川崎成美です"]
    },
    {
      "identity": "goto_rara",
      "name": "後藤楽々",
      "generation": 7,
      "keywords": [
        "後藤楽々です",
        "La",
        "楽々が中々会",
        "楽々の宝物",
        "楽々の嬉しかった事"
      ]
    },
    {
      "identity": "suenaga_oka",
      "name": "末永桜花",
      "generation": 7,
      "keywords": ["末永桜花です"]
    },
    {
      "identity": "sugiyama_aika",
      "name": "杉山愛佳",
      "generation": 7,
      "keywords": ["あいあい日記"]
    },
    {
      "identity": "takahata_yuki",
      "name": "髙畑結希",
      "generation": 7,
      "keywords": ["高畑結希です"]
    }
  ],
  "ken81": [
    {
      "identity": "atsumi_ayaha",
      "name": "渥美彩羽",
      "generation": 8,
      "keywords": ["あや♪"]
    },
    {
      "identity": "ishikawa_saki",
      "name": "石川咲姫",
      "generation": 8,
      "keywords": ["さきりんスマイルブログ", "石川咲姫です"]
    },
    {
      "identity": "ishiguro_yuzuki",
      "name": "石黒友月",
      "generation": 8,
      "keywords": ["ゆづき☆彡"]
    },
    {
      "identity": "inoue_ruka",
      "name": "井上瑠夏",
      "generation": 8,
      "keywords": ["るかのブログ", "るか、初めてブログる"]
    },
    {
      "identity": "oshiba_rinka",
      "name": "大芝りんか",
      "generation": 8,
      "keywords": ["りんかちゃんですよ"]
    },
    {
      "identity": "okada_miku",
      "name": "岡田美紅",
      "generation": 8,
      "keywords": ["みぃぽぽBlog"]
    }
  ],
  "ken82": [
    {
      "identity": "kitagawa_yoshino",
      "name": "北川愛乃",
      "generation": 8,
      "keywords": [
        "北川愛乃と",
        "よこにゃんの",
        "のよこにゃん",
        "よこにゃんbBlog",
        "よこにゃんBlog"
      ]
    },
    {
      "identity": "kawai_anna",
      "name": "川合杏奈",
      "generation": 8,
      "keywords": ["川合杏奈（あんたん）です", "☆杏奈", "杏奈☆", "あんたん☆"]
    },
    {
      "identity": "kurashima_ami",
      "name": "倉島杏実",
      "generation": 8,
      "keywords": ["あみちゃん♪", "倉島杏実です"]
    },
    {
      "identity": "sakamoto_marin",
      "name": "坂本真凛",
      "generation": 8,
      "keywords": ["まりんぶろぐ"]
    },
    {
      "identity": "sato_kaho",
      "name": "佐藤佳穂",
      "generation": 8,
      "keywords": ["佐藤佳穂です"]
    },
    {
      "identity": "shirayuki_kohaku",
      "name": "白雪希明",
      "generation": 8,
      "keywords": ["こはちゃん日記"]
    },
    {
      "identity": "yahagi_yukina",
      "name": "矢作有紀奈",
      "generation": 8,
      "keywords": ["ゆきなです", "矢作有紀奈です"]
    }
  ],
  "ken83": [
    {
      "identity": "sato_kaho",
      "name": "佐藤佳穂",
      "generation": 8,
      "keywords": ["佐藤佳穂です"]
    },
    {
      "identity": "shirayuki_kohaku",
      "name": "白雪希明",
      "generation": 8,
      "keywords": ["こはちゃん日記"]
    },
    {
      "identity": "nakamura_izumi",
      "name": "仲村和泉",
      "generation": 8,
      "keywords": ["仲村 和泉です", "いずりんさんだよ"]
    },
    {
      "identity": "nonogaki_miki",
      "name": "野々垣美希",
      "generation": 8,
      "keywords": ["ののがきみきですわ", "ののがきみき♪", "ののがき みき"]
    },
    {
      "identity": "nomura_miyo",
      "name": "野村実代",
      "generation": 8,
      "keywords": ["みよまるの", "みよまる参上"]
    },
    {
      "identity": "morihira_riko",
      "name": "森平莉子",
      "generation": 8,
      "keywords": ["ノりこりん", "森平莉子です", "りこりんこと森平莉子"]
    },
    {
      "identity": "fukai_negai",
      "name": "深井ねがい",
      "generation": 8,
      "keywords": [
        "深井ねがいです",
        "ねがいの",
        "ねがいでーす",
        "ねがいです",
        "ねがいぶろぐです",
        "ねがいブログ"
      ]
    }
  ],
  "ken01": [
    {
      "identity": "atsumi_ayaha",
      "name": "渥美彩羽",
      "generation": 8,
      "keywords": ["あや♪"]
    },
    {
      "identity": "ishikawa_saki",
      "name": "石川咲姫",
      "generation": 8,
      "keywords": ["さきりんスマイルブログ", "石川咲姫です"]
    },
    {
      "identity": "ishiguro_yuzuki",
      "name": "石黒友月",
      "generation": 8,
      "keywords": ["ゆづき☆彡"]
    },
    {
      "identity": "oshiba_rinka",
      "name": "大芝りんか",
      "generation": 8,
      "keywords": ["りんかちゃんですよ"]
    },
    {
      "identity": "okada_miku",
      "name": "岡田美紅",
      "generation": 8,
      "keywords": ["みぃぽぽBlog"]
    },
    {
      "identity": "kurashima_ami",
      "name": "倉島杏実",
      "generation": 8,
      "keywords": ["あみちゃん♪", "倉島杏実です"]
    }
  ],
  "ken02": [
    {
      "identity": "kurashima_ami",
      "name": "倉島杏実",
      "generation": 8,
      "keywords": ["あみちゃん♪", "倉島杏実です"]
    },
    {
      "identity": "sakamoto_marin",
      "name": "坂本真凛",
      "generation": 8,
      "keywords": ["まりんぶろぐ"]
    },
    {
      "identity": "shirayuki_kohaku",
      "name": "白雪希明",
      "generation": 8,
      "keywords": ["こはちゃん日記"]
    },
    {
      "identity": "nakamura_izumi",
      "name": "仲村和泉",
      "generation": 8,
      "keywords": ["仲村 和泉です", "いずりんさんだよ"]
    },
    {
      "identity": "nonogaki_miki",
      "name": "野々垣美希",
      "generation": 8,
      "keywords": ["ののがきみきですわ", "ののがきみき♪", "ののがき みき"]
    },
    {
      "identity": "fukai_negai",
      "name": "深井ねがい",
      "generation": 8,
      "keywords": [
        "深井ねがいです",
        "ねがいの",
        "ねがいでーす",
        "ねがいです",
        "ねがいぶろぐです",
        "ねがいブログ"
      ]
    },
    {
      "identity": "morihira_riko",
      "name": "森平莉子",
      "generation": 8,
      "keywords": ["ノりこりん", "森平莉子です", "りこりんこと森平莉子"]
    },
    {
      "identity": "wada_aina",
      "name": "和田愛菜",
      "generation": 7,
      "keywords": ["あいな"]
    }
  ],
  "ken001": [
    {
      "identity": "atsumi_ayaha",
      "name": "渥美彩羽",
      "generation": 8,
      "keywords": ["あや♪"]
    },
    {
      "identity": "ishikawa_saki",
      "name": "石川咲姫",
      "generation": 8,
      "keywords": ["さきりんスマイルブログ", "石川咲姫です"]
    },
    {
      "identity": "ishiguro_yuzuki",
      "name": "石黒友月",
      "generation": 8,
      "keywords": ["ゆづき☆彡"]
    },
    {
      "identity": "fukai_negai",
      "name": "深井ねがい",
      "generation": 8,
      "keywords": [
        "深井ねがいです",
        "ねがいの",
        "ねがいでーす",
        "ねがいです",
        "ねがいぶろぐです",
        "ねがいブログ"
      ]
    },
    {
      "identity": "morihira_riko",
      "name": "森平莉子",
      "generation": 8,
      "keywords": ["ノりこりん", "森平莉子です", "りこりんこと森平莉子"]
    }
  ],
  "draft3": [
    {
      "identity": "otani_yuki",
      "name": "大谷悠妃",
      "generation": "d3",
      "keywords": ["ゆうゆブログ"]
    },
    {
      "identity": "kozuma_honoka",
      "name": "上妻ほの香",
      "generation": "d3",
      "keywords": ["いらーっしゃい"]
    },
    {
      "identity": "nakano_airi",
      "name": "中野愛理",
      "generation": "d3",
      "keywords": ["なかのあいりです"]
    },
    {
      "identity": "nishi_marina",
      "name": "西満里奈",
      "generation": "d3",
      "keywords": [
        "ニ シ マ リ ナ ブ ロ グ",
        "ニ シ マ リ ナ",
        "ニ シ マ リ ナ フ ゛ロ グ"
      ]
    },
    {
      "identity": "hirata_shiina",
      "name": "平田詩奈",
      "generation": "d3",
      "keywords": ["しぃちゃんBlog", "しぃちゃん Blog"]
    }
  ],
  "ken91": [
    {
      "identity": "aoumi_hinano",
      "name": "青海ひな乃",
      "generation": 9,
      "keywords": ["ぴよlog"]
    },
    {
      "identity": "akahori_kimie",
      "name": "赤堀君江",
      "generation": 9,
      "keywords": ["君江", "あかほりきみえ"]
    },
    {
      "identity": "arano_himeka",
      "name": "荒野姫楓",
      "generation": 9,
      "keywords": ["たんたんひめたん", "初めましてのひめたん"]
    },
    {
      "identity": "ikeda_kaede",
      "name": "池田楓",
      "generation": 9,
      "keywords": ["かえにゃん。", "かえにゃんです", "にゃんにゃんかえにゃん"]
    },
    {
      "identity": "ishikawa_kanon",
      "name": "石川花音",
      "generation": 9,
      "keywords": [
        "石川花音です",
        "きゃのんてぃのブログ",
        "きゃのんてぃのTEA ROOM"
      ]
    }
  ],
  "ken92": [
    {
      "identity": "iriuchijima_sayaka",
      "name": "入内嶋涼",
      "generation": 9,
      "keywords": ["さあやだより", "いりうちじま"]
    },
    {
      "identity": "ohashi_mako",
      "name": "大橋真子",
      "generation": 9,
      "keywords": ["わーい", "おつまこ"]
    },
    {
      "identity": "oba_sayaka",
      "name": "大場紗也加",
      "generation": 9,
      "keywords": ["おおさやブログ"]
    },
    {
      "identity": "okamoto_ayaka",
      "name": "岡本彩夏",
      "generation": 9,
      "keywords": ["あーーや"]
    },
    {
      "identity": "kawashima_miharu",
      "name": "川嶋美晴",
      "generation": 9,
      "keywords": ["みはるんぶろぐ"]
    }
  ],
  "ken93": [
    {
      "identity": "shirai_yukino",
      "name": "白井友紀乃",
      "generation": 9,
      "keywords": ["ゆっちーず日記", "もう一つの理由"]
    },
    {
      "identity": "sugiyama_natalie",
      "name": "杉山菜田里",
      "generation": 9,
      "keywords": ["なたりんGo"]
    },
    {
      "identity": "suzuki_ena",
      "name": "鈴木愛菜",
      "generation": 9,
      "keywords": ["えなたんblog"]
    },
    {
      "identity": "suzuki_kokona",
      "name": "鈴木恋奈",
      "generation": 9,
      "keywords": ["鈴木恋奈です"]
    },
    {
      "identity": "takeuchi_nanami",
      "name": "竹内ななみ",
      "generation": 9,
      "keywords": ["なななななななーやん", "竹内ななみ"]
    }
  ],
  "ken94": [
    {
      "identity": "tanabe_mizuki",
      "name": "田辺美月",
      "generation": 9,
      "keywords": ["田辺美月です"]
    },
    {
      "identity": "nakasaka_miyu",
      "name": "中坂美祐",
      "generation": 9,
      "keywords": ["ぶーろぐ"]
    },
    {
      "identity": "hirano_momona",
      "name": "平野百菜",
      "generation": 9,
      "keywords": [
        "もものもりもり日記",
        "もものモリモリ日記",
        "ももたんです",
        "ももたんブログ"
      ]
    },
    {
      "identity": "fujimoto_fuyuka",
      "name": "藤本冬香",
      "generation": 9,
      "keywords": ["藤本冬香です"]
    }
  ]
}
